helloworldpip/__init__.py
helloworldpip/helloworld.py
helloworldpip-0.0.1.dist-info/LICENSE
helloworldpip-0.0.1.dist-info/METADATA
helloworldpip-0.0.1.dist-info/WHEEL
helloworldpip-0.0.1.dist-info/top_level.txt
helloworldpip-0.0.1.dist-info/RECORD
