Metadata-Version: 2.1
Name: helloworldpip
Version: 0.0.1
Summary: Demo Program to Print Hello World
Author: devsumitg
Author-email: <devsumitg@gmail.com>
Keywords: python,hello world,pip
Classifier: Development Status :: 1 - Planning
Classifier: Intended Audience :: Developers
Classifier: Programming Language :: Python :: 3
Classifier: Operating System :: Unix
Classifier: Operating System :: MacOS :: MacOS X
Classifier: Operating System :: Microsoft :: Windows
License-File: LICENSE
